{
  "project_info": {
    "project_number": "494072390513",
    "project_id": "plantinsta-7379f",
    "storage_bucket": "plantinsta-7379f.appspot.com"
  },
  "client": [
    {
      "client_info": {
        "mobilesdk_app_id": "1{\n  \"project_info\": {\n    \"project_number\": \"494072390513\",\n    \"project_id\": \"plantinsta-7379f\",\n    \"storage_bucket\": \"plantinsta-7379f.appspot.com\"\n  },\n  \"client\": [\n    {\n      \"client_info\": {\n        \"mobilesdk_app_id\": \"1:494072390513:android:2c7680b01e4c96e05e8cd0\",\n        \"android_client_info\": {\n          \"package_name\": \"com.zlpls.plantinsta\"\n        }\n      },\n      \"oauth_client\": [\n        {\n          \"client_id\": \"494072390513-1j9c09scbmv6rm0gbulsrauqubm9taks.apps.googleusercontent.com\",\n          \"client_type\": 1,\n          \"android_info\": {\n            \"package_name\": \"com.zlpls.plantinsta\",\n            \"certificate_hash\": \"13ef27562cf49869b7e8681c6cadbc7d54da3eef\"\n          }\n        },\n        {\n          \"client_id\": \"494072390513-a51ubecdcbl8f909ukq3udmkrt0isc98.apps.googleusercontent.com\",\n          \"client_type\": 1,\n          \"android_info\": {\n            \"package_name\": \"com.zlpls.plantinsta\",\n            \"certificate_hash\": \"f8bf1035d684b62e46e26d5e4ddafa87ec8eb2eb\"\n          }\n        },\n        {\n          \"client_id\": \"494072390513-ndreovqft2bh8m6tfqko80nsg0b6aho5.apps.googleusercontent.com\",\n          \"client_type\": 1,\n          \"android_info\": {\n            \"package_name\": \"com.zlpls.plantinsta\",\n            \"certificate_hash\": \"d9b07fc5f5b4d18ec99df7be9eeff67fd0dfecbb\"\n          }\n        },\n        {\n          \"client_id\": \"494072390513-9uc5rva4mnoedo1df62519nqoeatd4at.apps.googleusercontent.com\",\n          \"client_type\": 3\n        }\n      ],\n      \"api_key\": [\n        {\n          \"current_key\": \"AIzaSyCy-l9RkysfbfLWKUZyrbPdctfVGMYCKzM\"\n        }\n      ],\n      \"services\": {\n        \"appinvite_service\": {\n          \"other_platform_oauth_client\": [\n            {\n              \"client_id\": \"494072390513-9uc5rva4mnoedo1df62519nqoeatd4at.apps.googleusercontent.com\",\n              \"client_type\": 3\n            },\n            {\n              \"client_id\": \"494072390513-g6uhorh29e71akhojh31tl2uhqsvsjet.apps.googleusercontent.com\",\n              \"client_type\": 2,\n              \"ios_info\": {\n                \"bundle_id\": \"zlpls.PlantInsta\"\n              }\n            }\n          ]\n        }\n      }\n    }\n  ],\n  \"configuration_version\": \"1\"\n}:494072390513:android:2c7680b01e4c96e05e8cd0",
        "android_client_info": {
          "package_name": "com.zlpls.plantinsta"
        }
      },
      "oauth_client": [
        {
          "client_id": "494072390513-1j9c09scbmv6rm0gbulsrauqubm9taks.apps.googleusercontent.com",
          "client_type": 1,
          "android_info": {
            "package_name": "com.zlpls.plantinsta",
            "certificate_hash": "13ef27562cf49869b7e8681c6cadbc7d54da3eef"
          }
        },
        {
          "client_id": "494072390513-ndreovqft2bh8m6tfqko80nsg0b6aho5.apps.googleusercontent.com",
          "client_type": 1,
          "android_info": {
            "package_name": "com.zlpls.plantinsta",
            "certificate_hash": "d9b07fc5f5b4d18ec99df7be9eeff67fd0dfecbb"
          }
        },
        {
          "client_id": "494072390513-9uc5rva4mnoedo1df62519nqoeatd4at.apps.googleusercontent.com",
          "client_type": 3
        }
      ],
      "api_key": [
        {
          "current_key": "AIzaSyCy-l9RkysfbfLWKUZyrbPdctfVGMYCKzM"
        }
      ],
      "services": {
        "appinvite_service": {
          "other_platform_oauth_client": [
            {
              "client_id": "494072390513-9uc5rva4mnoedo1df62519nqoeatd4at.apps.googleusercontent.com",
              "client_type": 3
            },
            {
              "client_id": "494072390513-g6uhorh29e71akhojh31tl2uhqsvsjet.apps.googleusercontent.com",
              "client_type": 2,
              "ios_info": {
                "bundle_id": "zlpls.PlantInsta"
              }
            }
          ]
        }
      }
    }
  ],
  "configuration_version": "1"
}